Workbook

Sheet Transactions
A1: Session_ID | B1: Date | C1: Time | D1: Product_ID | E1: Product_Name | F1: Category | G1: Brand | H1: Weight | I1: Unit_Price_INR | J1: Quantity | K1: Total_Price_INR | L1: Payment_Method
A2: S001 | B2: 2025-05-01 | C2: 10:15 | D2: P001 | E2: Rice | F2: Staples | G2: India Gate | H2: 1kg | I2: 50 | J2: 3 | K2: =I2*J2 | L2: UPI
A3: S001 | B3: 2025-05-01 | C3: 10:15 | D3: P002 | E3: Milk | F3: Dairy | G3: Amul | H3: 1L | I3: 60 | J3: 2 | K3: =I3*J3 | L3: UPI
A4: S001 | B4: 2025-05-01 | C4: 10:15 | D4: P004 | E4: Eggs | F4: Protein | G4: Farm Fresh | H4: 12pcs | I4: 80 | J4: 1 | K4: =I4*J4 | L4: UPI
A5: S001 | B5: 2025-05-01 | C5: 10:15 | D5: P003 | E5: Bread | F5: Bakery | G5: Britannia | H5: 400g | I5: 40 | J5: 2 | K5: =I5*J5 | L5: UPI
A6: S002 | B6: 2025-05-02 | C6: 11:30 | D6: P001 | E6: Rice | F6: Staples | G6: India Gate | H6: 1kg | I6: 50 | J6: 2 | K6: =I6*J6 | L6: Card
A7: S002 | B7: 2025-05-02 | C7: 11:30 | D7: P004 | E7: Eggs | F7: Protein | G7: Farm Fresh | H7: 12pcs | I7: 80 | J7: 2 | K7: =I7*J7 | L7: Card
A8: S002 | B8: 2025-05-02 | C8: 11:30 | D8: P005 | E8: Oil | F8: Cooking | G8: Fortune | H8: 1L | I8: 120 | J8: 2 | K8: =I8*J8 | L8: Card
A9: S003 | B9: 2025-05-03 | C9: 09:45 | D9: P002 | E9: Milk | F9: Dairy | G9: Amul | H9: 1L | I9: 60 | J9: 2 | K9: =I9*J9 | L9: Cash
A10: S003 | B10: 2025-05-03 | C10: 09:45 | D10: P001 | E10: Rice | F10: Staples | G10: India Gate | H10: 1kg | I10: 50 | J10: 1 | K10: =I10*J10 | L10: Cash
A11: S003 | B11: 2025-05-03 | C11: 09:45 | D11: P003 | E11: Bread | F11: Bakery | G11: Britannia | H11: 400g | I11: 40 | J11: 2 | K11: =I11*J11 | L11: Cash
A12: S003 | B12: 2025-05-03 | C12: 09:45 | D12: P005 | E12: Oil | F12: Cooking | G12: Fortune | H12: 1L | I12: 120 | J12: 1 | K12: =I12*J12 | L12: Cash
A13: S004 | B13: 2025-05-05 | C13: 14:00 | D13: P003 | E13: Bread | F13: Bakery | G13: Britannia | H13: 400g | I13: 40 | J13: 2 | K13: =I13*J13 | L13: UPI
... A35: S010 | B35: 2025-05-14 | C35: 11:00 | D35: P005 | E35: Oil | F35: Cooking | G35: Fortune | H35: 1L | I35: 120 | J35: 2 | K35: =I35*J35 | L35: UPI

Sheet Summary
A1: SEAMLESS SHOPPING — TRANSACTION SUMMARY
A3: Product-wise Analysis
A4: Product | B4: Category | C4: Total Qty Sold | D4: Total Revenue (₹) | E4: Avg Price (₹)
A5: Rice | B5: Staples | C5: =SUMIF(Transactions!E:E,A5,Transactions!J:J) | D5: =SUMIF(Transactions!E:E,A5,Transactions!K:K) | E5: =D5/C5
A6: Milk | B6: Dairy | C6: =SUMIF(Transactions!E:E,A6,Transactions!J:J) | D6: =SUMIF(Transactions!E:E,A6,Transactions!K:K) | E6: =D6/C6
A7: Bread | B7: Bakery | C7: =SUMIF(Transactions!E:E,A7,Transactions!J:J) | D7: =SUMIF(Transactions!E:E,A7,Transactions!K:K) | E7: =D7/C7
A8: Eggs | B8: Protein | C8: =SUMIF(Transactions!E:E,A8,Transactions!J:J) | D8: =SUMIF(Transactions!E:E,A8,Transactions!K:K) | E8: =D8/C8
A9: Oil | B9: Cooking | C9: =SUMIF(Transactions!E:E,A9,Transactions!J:J) | D9: =SUMIF(Transactions!E:E,A9,Transactions!K:K) | E9: =D9/C9
A10: TOTAL | C10: =SUM(C5:C9) | D10: =SUM(D5:D9) | E10: =D10/C10
A12: Payment Method Analysis
A13: Payment Method | B13: No. of Sessions | C13: Total Revenue (₹)
A14: UPI | B14: =COUNTIF(Transactions!L:L,A14) | C14: =SUMIF(Transactions!L:L,A14,Transactions!K:K)
A15: Card | B15: =COUNTIF(Transactions!L:L,A15) | C15: =SUMIF(Transactions!L:L,A15,Transactions!K:K)
A16: Cash | B16: =COUNTIF(Transactions!L:L,A16) | C16: =SUMIF(Transactions!L:L,A16,Transactions!K:K)
A18: Key Metrics
A19: Total Sessions | B19: =COUNTA(UNIQUE(Transactions!A2:A102))-1
A20: Total Transactions | B20: =COUNTA(Transactions!A2:A102)-1
A21: Total Revenue (₹) | B21: =SUM(Transactions!K:K)
A22: Average Cart Value (₹) | B22: =SUM(Transactions!K:K)/10
A23: Most Popular Product | B23: Rice
A24: Top Payment Method | B24: UPI
